dytimer.py
dytimer-0.0.5.dist-info/METADATA
dytimer-0.0.5.dist-info/WHEEL
dytimer-0.0.5.dist-info/top_level.txt
dytimer-0.0.5.dist-info/RECORD
