Metadata-Version: 2.1
Name: dytimer
Version: 0.0.5
Summary: Dynamic timer to learn the update frequency of a resource on the web
Home-page: https://github.com/upperwal
Author: Abhishek Upperwal
Author-email: mesh@soket.in
License: UNKNOWN
Platform: UNKNOWN
Classifier: Programming Language :: Python :: 3
Classifier: License :: OSI Approved :: MIT License
Classifier: Operating System :: OS Independent
Requires-Dist: schedule
Requires-Dist: deepdiff
Requires-Dist: pytz
